line_ui/__init__.py
lineui-0.1.2.dist-info/LICENSE
lineui-0.1.2.dist-info/METADATA
lineui-0.1.2.dist-info/WHEEL
lineui-0.1.2.dist-info/top_level.txt
lineui-0.1.2.dist-info/RECORD
